src/__init__.py
src/binsearch.py
src/dsu.py
src/fft.py
src/fmath.py
src/fpow.py
src/gcf.py
src/heap.py
src/knapsack.py
src/powerset.py
src/search.py
src/sufar.py
src/graph/__init__.py
src/graph/agraph.py
src/graph/concomp.py
src/graph/graph.py
src/graph/mst.py
src/graph/spt.py
src/graph/wgraph.py
src/sort/__init__.py
src/sort/countsort.py
src/sort/heapsort.py
src/sort/insertsort.py
src/sort/mergesort.py
src/sort/quicksort.py
src/sort/selectsort.py
src/sort/shellsort.py
src/sset/__init__.py
src/sset/trie.py
src/sset/tst.py
test/__init__.py
test/test_binsearch.py
test/test_dsu.py
test/test_fmath.py
test/test_fpow.py
test/test_gcf.py
test/test_heap.py
test/test_knapsack.py
test/test_search.py
test/test_sufar.py
test/test_graph/__init__.py
test/test_graph/test_concomp.py
test/test_graph/test_graph.py
test/test_graph/test_mst.py
test/test_graph/test_spt.py
test/test_graph/test_wgraph.py
test/test_sort/__init__.py
test/test_sort/test_sort.py
test/test_sset/__init__.py
test/test_sset/test_sset.py
test/test_sset/test_tst.py
test/test_tree/__init__.py
test/test_tree/test_bst.py
test/test_tree/test_range_tree.py
test/test_tree/test_rbt.py
algos_py-0.5.1.dist-info/LICENSE
algos_py-0.5.1.dist-info/METADATA
algos_py-0.5.1.dist-info/WHEEL
algos_py-0.5.1.dist-info/top_level.txt
algos_py-0.5.1.dist-info/RECORD
