Metadata-Version: 2.1
Name: algos-py
Version: 0.5.1
Summary: Classic computer science algorithms in Python
Home-page: https://github.com/algos-all/algos-py
Author: Aleksandr Lisianoi
Author-email: alisianoi@protonmail.com
License: MIT
Platform: linux
Platform: windows
Platform: macos
License-File: LICENSE
